LICENSE
README.md
setup.cfg
setup.py
bin/logdaemon.py
bin/optcomplete.bash
bin/startlogdaemon.sh
lib/vsc/__init__.py
lib/vsc/utils/__init__.py
lib/vsc/utils/affinity.py
lib/vsc/utils/asyncprocess.py
lib/vsc/utils/daemon.py
lib/vsc/utils/dateandtime.py
lib/vsc/utils/docs.py
lib/vsc/utils/exceptions.py
lib/vsc/utils/fancylogger.py
lib/vsc/utils/frozendict.py
lib/vsc/utils/generaloption.py
lib/vsc/utils/groups.py
lib/vsc/utils/mail.py
lib/vsc/utils/missing.py
lib/vsc/utils/optcomplete.py
lib/vsc/utils/patterns.py
lib/vsc/utils/rest.py
lib/vsc/utils/run.py
lib/vsc/utils/testing.py
lib/vsc/utils/wrapper.py
lib/vsc_base.egg-info/PKG-INFO
lib/vsc_base.egg-info/SOURCES.txt
lib/vsc_base.egg-info/dependency_links.txt
lib/vsc_base.egg-info/namespace_packages.txt
lib/vsc_base.egg-info/requires.txt
lib/vsc_base.egg-info/top_level.txt