Metadata-Version: 2.1
Name: vsc-base
Version: 3.6.1
Summary: Common tools used within our organization. Originally created by the HPC team of Ghent University (https://ugent.be/hpc).
Home-page: https://github.com/hpcugent/vsc-base
Download-URL: 
Author: Stijn De Weirdt;Jens Timmerman;Andy Georges;Kenneth Hoste
Author-email: stijn.deweirdt@ugent.be, jens.timmerman@ugent.be, andy.georges@ugent.be, kenneth.hoste@ugent.be
Maintainer: Stijn De Weirdt;Jens Timmerman;Andy Georges;Kenneth Hoste;Wouter Depypere
Maintainer-email: stijn.deweirdt@ugent.be, jens.timmerman@ugent.be, andy.georges@ugent.be, kenneth.hoste@ugent.be, wouter.depypere@ugent.be
License: LGPLv2+
Classifier: License :: OSI Approved :: GNU Lesser General Public License v2 or later (LGPLv2+)
License-File: LICENSE
